eikonalfm/__init__.py
eikonalfm/cfm.cpp
eikonalfm/cfm.cpython-312-i386-linux-gnu.so
eikonalfm/cfm.pyi
eikonalfm/factoredmarcher.cpp
eikonalfm/factoredmarcher.hpp
eikonalfm/heap.cpp
eikonalfm/marcher.cpp
eikonalfm/marcher.hpp
eikonalfm-0.9.8.dist-info/METADATA
eikonalfm-0.9.8.dist-info/WHEEL
eikonalfm-0.9.8.dist-info/top_level.txt
eikonalfm-0.9.8.dist-info/RECORD
eikonalfm-0.9.8.dist-info/licenses/LICENSE
