Metadata-Version: 2.4
Name: eikonalfm
Version: 0.9.8
Summary: Solving the (factored) eikonal equation with the Fast Marching method
Author-email: Kevin Ganster <kevinganster@gmail.com>
License: MIT
Project-URL: Homepage, https://github.com/kevinganster/eikonalfm
Project-URL: Issues, https://github.com/kevinganster/eikonalfm/issues
Keywords: Fast Marching method,factored Fast Marching method,eikonal equation,factored eikonal equation
Classifier: Operating System :: OS Independent
Classifier: Topic :: Scientific/Engineering :: Mathematics
Classifier: Programming Language :: C++
Classifier: Programming Language :: Python :: 3
Requires-Python: >=3.7
License-File: LICENSE
Requires-Dist: numpy>=1.7
Dynamic: license
Dynamic: license-file
